LICENSE
MANIFEST.in
README.rst
setup.cfg
setup.py
src/scsequtil/__init__.py
src/scsequtil/align.py
src/scsequtil/bam.py
src/scsequtil/fasta.py
src/scsequtil/fastq.py
src/scsequtil/gtf.py
src/scsequtil/mp.py
src/scsequtil/reader.py
src/scsequtil/table.py
src/scsequtil.egg-info/PKG-INFO
src/scsequtil.egg-info/SOURCES.txt
src/scsequtil.egg-info/dependency_links.txt
src/scsequtil.egg-info/entry_points.txt
src/scsequtil.egg-info/requires.txt
src/scsequtil.egg-info/top_level.txt
src/scsequtil/css/style.css
src/scsequtil/html_/pdf_table.html
src/scsequtil/plot/__init__.py
src/scsequtil/plot/grid.py
src/scsequtil/plot/scatter.py
src/scsequtil/test/__init__.py
src/scsequtil/test/bam.py
src/scsequtil/test/fastq.py
src/scsequtil/test/gtf.py
src/scsequtil/test/table.py
src/scsequtil/test/data/test.bam
src/scsequtil/test/data/test.bam.bai
src/scsequtil/test/data/test.gtf
src/scsequtil/test/data/test.gtf.bz2
src/scsequtil/test/data/test.gtf.gz
src/scsequtil/test/data/test.sam
src/scsequtil/test/data/test_i7.fastq
src/scsequtil/test/data/test_i7.fastq.bz2
src/scsequtil/test/data/test_i7.fastq.gz
src/scsequtil/test/data/test_r1.fastq
src/scsequtil/test/data/test_r1.fastq.bz2
src/scsequtil/test/data/test_r1.fastq.gz
src/scsequtil/test/data/test_r2.bam
src/scsequtil/test/data/test_r2.fastq
src/scsequtil/test/data/test_r2.fastq.bz2
src/scsequtil/test/data/test_r2.fastq.gz
src/scsequtil/test/data/test_r2_tagged.bam