Metadata-Version: 1.1
Name: scsequtil
Version: 0.0.6
Summary: Utilities for large scale single cell data processing
Home-page: https://github.com/ambrosejcarr/scsequtil.git
Author: Ambrose J. Carr
Author-email: mail@ambrosejcarr.com
License: UNKNOWN
Platform: UNKNOWN
Classifier: Development Status :: 4 - Beta
Classifier: Natural Language :: English
Classifier: License :: OSI Approved :: GNU General Public License v2 (GPLv2)
Classifier: Operating System :: OS Independent
Classifier: Programming Language :: Python
Classifier: Programming Language :: Python :: 3
Classifier: Programming Language :: Python :: 3.3
Classifier: Programming Language :: Python :: 3.4
Classifier: Programming Language :: Python :: 3.5
Classifier: Programming Language :: Python :: 3.6
Classifier: Programming Language :: Python :: Implementation :: PyPy
Classifier: Topic :: Scientific/Engineering :: Bio-Informatics
